lambdaguard/__init__.py
lambdaguard/__version__.py
lambdaguard/assets/func.html
lambdaguard/assets/funclist.html
lambdaguard/assets/funcvuln.html
lambdaguard/assets/highcharts-theme.js
lambdaguard/assets/highcharts.js
lambdaguard/assets/index.html
lambdaguard/assets/layer.html
lambdaguard/assets/layerlist.html
lambdaguard/assets/logo.png
lambdaguard/assets/stats.html
lambdaguard/assets/stats.js
lambdaguard/assets/statsitem.html
lambdaguard/assets/vuln.html
lambdaguard/assets/vulnlist.html
lambdaguard/core/APIGateway.py
lambdaguard/core/AWS.py
lambdaguard/core/DynamoDB.py
lambdaguard/core/KMS.py
lambdaguard/core/Lambda.py
lambdaguard/core/Role.py
lambdaguard/core/S3.py
lambdaguard/core/SNS.py
lambdaguard/core/SQS.py
lambdaguard/core/STS.py
lambdaguard/core/__init__.py
lambdaguard/security/AccessControlList.py
lambdaguard/security/Encryption.py
lambdaguard/security/LambdaWrite.py
lambdaguard/security/PolicyStatement.py
lambdaguard/security/PrivilegeEscalation.py
lambdaguard/security/Public.py
lambdaguard/security/Report.py
lambdaguard/security/Scan.py
lambdaguard/security/SonarQube.py
lambdaguard/security/__init__.py
lambdaguard/utils/__init__.py
lambdaguard/utils/acl.py
lambdaguard/utils/arnparse.py
lambdaguard/utils/cli.py
lambdaguard/utils/iterator.py
lambdaguard/utils/log.py
lambdaguard/utils/paginator.py
lambdaguard/visibility/HTMLReport.py
lambdaguard/visibility/Report.py
lambdaguard/visibility/Statistics.py
lambdaguard/visibility/__init__.py
LambdaGuard-2.4.3.dist-info/LICENSE
LambdaGuard-2.4.3.dist-info/METADATA
LambdaGuard-2.4.3.dist-info/WHEEL
LambdaGuard-2.4.3.dist-info/entry_points.txt
LambdaGuard-2.4.3.dist-info/top_level.txt
LambdaGuard-2.4.3.dist-info/RECORD
