Metadata-Version: 2.1
Name: LambdaGuard
Version: 2.4.3
Summary: LambdaGuard
Home-page: https://github.com/Skyscanner/LambdaGuard
Author: Artëm Tsvetkov
Author-email: artem.tsvetkov@skyscanner.net
License: UNKNOWN
Platform: UNKNOWN
Requires-Python: >=3.6.3
Requires-Dist: boto3
Requires-Dist: argparse
Requires-Dist: requests
Provides-Extra: dev
Requires-Dist: black (==20.8b1) ; extra == 'dev'
Requires-Dist: coverage (==4.5.4) ; extra == 'dev'
Requires-Dist: flake8 (==3.8.4) ; extra == 'dev'
Requires-Dist: isort (==5.6.3) ; extra == 'dev'
Requires-Dist: pytest (==6.1.1) ; extra == 'dev'
Requires-Dist: pytest-mock (==3.3.1) ; extra == 'dev'
Requires-Dist: pip-tools (==5.3.1) ; extra == 'dev'
Requires-Dist: wheel (>=0.34.2) ; extra == 'dev'
Requires-Dist: twine (==3.2.0) ; extra == 'dev'
